jsonl/__init__.py
jsonl/jsonl.py
jsonl/parallel.py
jsonl2-1.1.14.dist-info/LICENSE
jsonl2-1.1.14.dist-info/METADATA
jsonl2-1.1.14.dist-info/WHEEL
jsonl2-1.1.14.dist-info/top_level.txt
jsonl2-1.1.14.dist-info/RECORD
