Metadata-Version: 2.1
Name: jsonl2
Version: 1.1.14
Summary: Json line library
Author-email: Pedro Mayorga <ppmayorga80@gmail.com>
Classifier: Programming Language :: Python :: 3
Classifier: License :: OSI Approved :: MIT License
Classifier: Operating System :: OS Independent
Requires-Python: >=3.7
License-File: LICENSE
Requires-Dist: smart-open
Requires-Dist: tqdm
